praxis/__init__.py
praxis/asserts.py
praxis/asserts_test.py
praxis/base_hyperparams.py
praxis/base_hyperparams_test.py
praxis/base_input.py
praxis/base_input_test.py
praxis/base_layer.py
praxis/base_layer_test.py
praxis/base_model.py
praxis/beam_search.py
praxis/beam_search_test.py
praxis/decoder_hparams.py
praxis/decoder_utils.py
praxis/decoder_utils_test.py
praxis/fiddle_tags.py
praxis/flat_beam_search.py
praxis/flat_beam_search_test.py
praxis/flax_utils.py
praxis/gshard_utils.py
praxis/lazy_loader.py
praxis/lingvo_lib.py
praxis/metric_utils.py
praxis/optimizer_prefix_vectorization.py
praxis/optimizer_prefix_vectorization_test.py
praxis/optimizers.py
praxis/optimizers_test.py
praxis/pax_fiddle.py
praxis/pax_fiddle_test.py
praxis/py_utils.py
praxis/py_utils_test.py
praxis/pytypes.py
praxis/pytypes_test.py
praxis/sample_decode.py
praxis/sample_decode_test.py
praxis/schedules.py
praxis/schedules_test.py
praxis/test_utils.py
praxis/token_samplers.py
praxis/token_samplers_test.py
praxis/trees.py
praxis/trees_test.py
praxis/layers/__init__.py
praxis/layers/activations.py
praxis/layers/activations_test.py
praxis/layers/adapters.py
praxis/layers/adapters_test.py
praxis/layers/attentions.py
praxis/layers/attentions_test.py
praxis/layers/augmentations.py
praxis/layers/augmentations_test.py
praxis/layers/base_ops.py
praxis/layers/bregman.py
praxis/layers/bregman_test.py
praxis/layers/checkpoint_policy.py
praxis/layers/chunk.py
praxis/layers/chunk_test.py
praxis/layers/conformers.py
praxis/layers/conformers_test.py
praxis/layers/convolutions.py
praxis/layers/convolutions_test.py
praxis/layers/ctc_objectives.py
praxis/layers/ctc_objectives_test.py
praxis/layers/einsum.py
praxis/layers/einsum_test.py
praxis/layers/embedding_softmax.py
praxis/layers/embedding_softmax_test.py
praxis/layers/flax_adapter.py
praxis/layers/flax_adapter_test.py
praxis/layers/frnn.py
praxis/layers/frnn_test.py
praxis/layers/glam.py
praxis/layers/gpu_fast_attention.py
praxis-1.4.0.dist-info/LICENSE
praxis-1.4.0.dist-info/METADATA
praxis-1.4.0.dist-info/WHEEL
praxis-1.4.0.dist-info/top_level.txt
praxis-1.4.0.dist-info/RECORD
