Metadata-Version: 2.1
Name: praxis
Version: 1.4.0
Summary: Functionalities such as a layers for building neural networks in Jax.
Home-page: https://github.com/google/praxis
Author: PAX team
Author-email: pax-dev@google.com
License: Apache-2.0
Platform: UNKNOWN
Classifier: Programming Language :: Python :: 3.10
Classifier: Programming Language :: Python :: 3.11
Requires-Python: >=3.10
License-File: LICENSE
Requires-Dist: absl-py (==1.4.0)
Requires-Dist: chex (>=0.1.85)
Requires-Dist: clu (==0.0.11)
Requires-Dist: einops (==0.7.0)
Requires-Dist: etils (==1.7.0)
Requires-Dist: fiddle (==0.3.0)
Requires-Dist: flax (==0.8.2)
Requires-Dist: jax-bitempered-loss (==0.0.2)
Requires-Dist: jax (==0.4.26)
Requires-Dist: jaxtyping (==0.2.28)
Requires-Dist: lingvo (==0.12.7)
Requires-Dist: numpy (==1.26.4)
Requires-Dist: opt-einsum (==3.3.0)
Requires-Dist: optax-shampoo (==0.0.6)
Requires-Dist: optax (==0.2.2)
Requires-Dist: sentencepiece (==0.1.99)
Requires-Dist: tensorflow-datasets (==4.8.3)
Requires-Dist: tensorflow-metadata (==1.12.0)
Requires-Dist: tensorflow-text (~=2.9.0)
Requires-Dist: tensorflow (~=2.9.2)
Requires-Dist: tfds-nightly (==4.8.3.dev202303280045)
Requires-Dist: typeguard (==2.13.3)
